ops_tracing/__init__.py
ops_tracing/_api.py
ops_tracing/_backend.py
ops_tracing/_buffer.py
ops_tracing/_export.py
ops_tracing/_mock.py
ops_tracing/py.typed
ops_tracing/vendor/charms/certificate_transfer_interface/v1/certificate_transfer.py
ops_tracing/vendor/charms/tempo_coordinator_k8s/v0/tracing.py
ops_tracing/vendor/otlp_json/__init__.py
ops_tracing/vendor/otlp_json/py.typed
ops_tracing/vendor/otlp_json/readme.md
ops_tracing-3.5.0.dist-info/METADATA
ops_tracing-3.5.0.dist-info/WHEEL
ops_tracing-3.5.0.dist-info/RECORD
