Metadata-Version: 2.4
Name: ops-tracing
Version: 3.5.0
Summary: The tracing facility for the Ops library.
Project-URL: Repository, https://github.com/canonical/operator
Project-URL: Issues, https://github.com/canonical/operator/issues
Project-URL: Documentation, https://documentation.ubuntu.com/ops/latest/
Project-URL: Changelog, https://github.com/canonical/operator/blob/main/CHANGES.md
Author: The Charm Tech team at Canonical Ltd.
License-Expression: Apache-2.0
Classifier: Development Status :: 5 - Production/Stable
Classifier: Framework :: OpenTelemetry
Classifier: Intended Audience :: Developers
Classifier: Intended Audience :: System Administrators
Classifier: Natural Language :: English
Classifier: Operating System :: MacOS :: MacOS X
Classifier: Operating System :: POSIX :: Linux
Classifier: Programming Language :: Python
Classifier: Programming Language :: Python :: 3
Classifier: Programming Language :: Python :: 3 :: Only
Classifier: Programming Language :: Python :: 3.10
Classifier: Programming Language :: Python :: 3.11
Classifier: Programming Language :: Python :: 3.12
Classifier: Programming Language :: Python :: 3.13
Classifier: Programming Language :: Python :: 3.14
Classifier: Programming Language :: Python :: Implementation :: CPython
Classifier: Programming Language :: Python :: Implementation :: PyPy
Classifier: Topic :: Software Development :: Libraries
Requires-Python: >=3.10
Requires-Dist: opentelemetry-api~=1.0
Requires-Dist: opentelemetry-sdk~=1.30
Requires-Dist: ops==3.5.0
Requires-Dist: pydantic
